jaketest/__init__.py
jaketest/adders.py
jaketest/subtracters.py
jaketest_jakedesantis-0.0.1.dist-info/LICENSE
jaketest_jakedesantis-0.0.1.dist-info/METADATA
jaketest_jakedesantis-0.0.1.dist-info/WHEEL
jaketest_jakedesantis-0.0.1.dist-info/top_level.txt
jaketest_jakedesantis-0.0.1.dist-info/RECORD
